[
  {
    "id": 1,
    "image": "https://vignette.wikia.nocookie.net/bobsburgerpedia/images/3/3c/Tina-8.jpg/revision/latest?cb=20150727150853",
    "clicked": false
  },
  {
    "id": 2,
    "image": "https://vignette.wikia.nocookie.net/bobsburgerpedia/images/e/ed/Teddy-4.jpg/revision/latest?cb=20150727151256",
    "clicked": false
  },
  {
    "id": 3,
    "image": "https://vignette.wikia.nocookie.net/bobsburgerpedia/images/0/00/Louise-4.jpg/revision/latest?cb=20150727150408",
    "clicked": false
  },
  {
    "id": 4,
    "image": "https://vignette.wikia.nocookie.net/bobsburgerpedia/images/c/cf/Linda-11.jpg/revision/latest?cb=20150727150059",
    "clicked": false
  },
  {
    "id": 5,
    "image": "https://vignette.wikia.nocookie.net/bobsburgerpedia/images/a/a1/Bob-13.jpg/revision/latest?cb=20150727145203",
    "clicked": false
  },
  {
    "id": 6,
    "image": "https://vignette.wikia.nocookie.net/bobsburgerpedia/images/9/99/Gene-2.jpg/revision/latest?cb=20150727145623",
    "clicked": false
  },
  {
    "id": 7,
    "image": "https://vignette.wikia.nocookie.net/bobsburgerpedia/images/8/8d/Regular-Rudy.jpg/revision/latest?cb=20160410170923",
    "clicked": false
  },
  {
    "id": 8,
    "image": "https://vignette.wikia.nocookie.net/bobsburgerpedia/images/7/76/Moolissa.jpg/revision/latest?cb=20150704173802",
    "clicked": false
  },
  {
    "id": 9,
    "image": "https://vignette.wikia.nocookie.net/bobsburgerpedia/images/1/1d/Phillip_Frond.png/revision/latest?cb=20150920220653",
    "clicked": false
  },
  {
    "id": 10,
    "image": "https://vignette.wikia.nocookie.net/bobsburgerpedia/images/b/bb/Andy_and_Ollie_Pesto.png/revision/latest?cb=20130306050002",
    "clicked": false
  },
  {
    "id": 11,
    "image": "https://vignette.wikia.nocookie.net/bobsburgerpedia/images/3/30/Tina-3.jpg/revision/latest?cb=20150727150851",
    "clicked": false
  },
  {
    "id": 12,
    "image": "https://vignette.wikia.nocookie.net/bobsburgerpedia/images/b/b7/Bob-1.jpg/revision/latest?cb=20150727145126",
    "clicked": false
  }
]



